magestore_aim/__init__.py
magestore_aim/auto.py
magestore_aim/data/magento_versions.json
magestore_aim/data/php_versions.json
magestore_aim-1.6.7.dist-info/LICENSE
magestore_aim-1.6.7.dist-info/METADATA
magestore_aim-1.6.7.dist-info/WHEEL
magestore_aim-1.6.7.dist-info/top_level.txt
magestore_aim-1.6.7.dist-info/RECORD
