Metadata-Version: 2.1
Name: magestore-aim
Version: 1.6.7
Summary: New magento version : 2.2.9 & 2.3.2
Home-page: https://magestore.com
Author: Mars
Author-email: mars@trueplus.vn
License: UNKNOWN
Platform: UNKNOWN
Classifier: Programming Language :: Python :: 3
Requires-Python: >=3
Requires-Dist: cryptography (>=2.5)
Requires-Dist: fabric
Requires-Dist: packaging
